IMM_to_ld.py
__init__.py
classify_characteristic.py
compute_lvl1_maturity_scores.py
compute_maturiy_scores.py
create_md_report.py
generate_report.py
generic_radar_plot.py
main.py
organizations_tube_in_the_cube.py
qid_to_answerValue.py
raw_data_to_maturityscore.py
respondents_tube_in_the_cube.py
responses_to_ld.py
snippet.py
subcapability_radar_plot.py
survey_to_ld.py
EminentReportingTool-0.0.1.dist-info/LICENSE
EminentReportingTool-0.0.1.dist-info/METADATA
EminentReportingTool-0.0.1.dist-info/WHEEL
EminentReportingTool-0.0.1.dist-info/top_level.txt
EminentReportingTool-0.0.1.dist-info/RECORD
