Metadata-Version: 2.1
Name: EminentReportingTool
Version: 0.0.1
Summary: A package to analyse and publish results from EMINEnT maturity assessment studies
Author-email: Joep van Genuchten <joep@uuidea.eu>
License: Apache License (2.0)
Project-URL: Homepage, https://github.com/int-net/EminentReportingTool
Project-URL: Issues, https://github.com/int-net/EminentReportingTool/issues
Classifier: Programming Language :: Python :: 3
Classifier: License :: OSI Approved :: Apache Software License
Classifier: Operating System :: OS Independent
Requires-Python: >=3.8
License-File: LICENSE
